<TakeList sourceAnimFile="Export\c1020\morphemeMarkup\a00_06_7013_Wep01_SideWalkLeft.xmd.xml" version="1">
  <Take name="untitled">
    <Attributes>
      <secondDuration type="double">1.5</secondDuration>
      <fps type="double">30</fps>
      <clipStart type="double">0</clipStart>
      <clipEnd type="double">1</clipEnd>
      <loop type="bool">false</loop>
    </Attributes>
    <DiscreteEventTrack name="Footsteps" guid="c424399e-39b7-4eae-8089-7a59b0cf0ac2" channelID="1">
      <Attributes>
        <userData type="uint">0</userData>
      </Attributes>
      <DiscreteEvent index="0">
        <Attributes>
          <userData type="uint">0</userData>
          <startTime type="double">0</startTime>
        </Attributes>
      </DiscreteEvent>
      <DiscreteEvent index="1">
        <Attributes>
          <userData type="uint">0</userData>
          <startTime type="double">0.488889</startTime>
        </Attributes>
      </DiscreteEvent>
    </DiscreteEventTrack>
    <DurationEventTrack name="TimeAct" guid="6dd1a214-6246-44b1-aba0-1e8cb25c7feb" channelID="4">
      <Attributes>
        <userData type="uint">1000</userData>
      </Attributes>
      <DurationEvent index="0">
        <Attributes>
          <userData type="uint">67013</userData>
          <startTime type="double">0</startTime>
          <duration type="double">1</duration>
        </Attributes>
      </DurationEvent>
    </DurationEventTrack>
  </Take>
</TakeList>