<TakeList sourceAnimFile="Export\c1020\morphemeMarkup\a00_09_7012_Wep02_Guard_HitLight.xmd.xml" version="1">
  <Take name="untitled">
    <Attributes>
      <secondDuration type="double">1</secondDuration>
      <fps type="double">30</fps>
      <clipStart type="double">0</clipStart>
      <clipEnd type="double">1</clipEnd>
      <loop type="bool">false</loop>
    </Attributes>
    <DiscreteEventTrack name="Footsteps" guid="e236b79e-459f-4370-b022-36283a3b1b0b" channelID="1">
      <Attributes>
        <userData type="uint">0</userData>
      </Attributes>
      <DiscreteEvent index="0">
        <Attributes>
          <userData type="uint">0</userData>
          <startTime type="double">0</startTime>
        </Attributes>
      </DiscreteEvent>
    </DiscreteEventTrack>
    <DurationEventTrack name="LeftSteps" guid="afbf5bd4-a25d-402c-9d5d-7789bf504101" channelID="2">
      <Attributes>
        <userData type="uint">10</userData>
      </Attributes>
      <DurationEvent index="0">
        <Attributes>
          <userData type="uint">10</userData>
          <startTime type="double">0</startTime>
          <duration type="double">1</duration>
        </Attributes>
      </DurationEvent>
    </DurationEventTrack>
    <DurationEventTrack name="RightSteps" guid="639fded7-ebbc-4ba9-b853-c0059307fb62" channelID="3">
      <Attributes>
        <userData type="uint">11</userData>
      </Attributes>
      <DurationEvent index="0">
        <Attributes>
          <userData type="uint">11</userData>
          <startTime type="double">0</startTime>
          <duration type="double">1</duration>
        </Attributes>
      </DurationEvent>
    </DurationEventTrack>
    <DurationEventTrack name="StateControl" guid="740a60f6-3a45-478e-9fa6-489a38bcb78e" channelID="13">
      <Attributes>
        <userData type="uint">80</userData>
      </Attributes>
      <DurationEvent index="0">
        <Attributes>
          <userData type="uint">80</userData>
          <startTime type="double">0.833333</startTime>
          <duration type="double">0.166667</duration>
        </Attributes>
      </DurationEvent>
    </DurationEventTrack>
    <DurationEventTrack name="TimeAct" guid="b9b7d139-103b-479d-9ee6-62de5838c94b" channelID="4">
      <Attributes>
        <userData type="uint">1000</userData>
      </Attributes>
      <DurationEvent index="0">
        <Attributes>
          <userData type="uint">97012</userData>
          <startTime type="double">0</startTime>
          <duration type="double">1</duration>
        </Attributes>
      </DurationEvent>
    </DurationEventTrack>
    <DurationEventTrack name="Guard" guid="9015fbe2-f053-4336-9849-b1280bd87bfa" channelID="16">
      <Attributes>
        <userData type="uint">500</userData>
      </Attributes>
      <DurationEvent index="0">
        <Attributes>
          <userData type="uint">520</userData>
          <startTime type="double">0</startTime>
          <duration type="double">1</duration>
        </Attributes>
      </DurationEvent>
    </DurationEventTrack>
    <DurationEventTrack name="GuardSpeedControl" guid="ed65f91e-a035-4ddb-a0cf-71b48bfd5267" channelID="17">
      <Attributes>
        <userData type="uint">500</userData>
      </Attributes>
      <DurationEvent index="0">
        <Attributes>
          <userData type="uint">550</userData>
          <startTime type="double">0.666667</startTime>
          <duration type="double">0.333333</duration>
        </Attributes>
      </DurationEvent>
    </DurationEventTrack>
    <DurationEventTrack name="GuardDistanceControl" guid="bcaee469-0225-48b9-a89f-9173a3c449c5" channelID="18">
      <Attributes>
        <userData type="uint">500</userData>
      </Attributes>
      <DurationEvent index="0">
        <Attributes>
          <userData type="uint">560</userData>
          <startTime type="double">0</startTime>
          <duration type="double">0.333333</duration>
        </Attributes>
      </DurationEvent>
    </DurationEventTrack>
    <DurationEventTrack name="DamageDuration" guid="0c5aa6da-28aa-4fbd-a94a-2b7074194631" channelID="8">
      <Attributes>
        <userData type="uint">200</userData>
      </Attributes>
      <DurationEvent index="0">
        <Attributes>
          <userData type="uint">250</userData>
          <startTime type="double">0</startTime>
          <duration type="double">0.833333</duration>
        </Attributes>
      </DurationEvent>
    </DurationEventTrack>
  </Take>
</TakeList>