<TakeList sourceAnimFile="morphemeMarkup\a75_01_7110_Wep01_StartUp_02_In.xmd.xml" version="1">
  <Take name="untitled">
    <Attributes>
      <secondDuration type="double">10</secondDuration>
      <fps type="double">30</fps>
      <clipStart type="double">0</clipStart>
      <clipEnd type="double">1</clipEnd>
      <loop type="bool">true</loop>
    </Attributes>
    <DiscreteEventTrack name="Footsteps" guid="4d8279f4-e8ab-48ac-b6c0-124a79b3820e" channelID="1">
      <Attributes>
        <userData type="uint">0</userData>
      </Attributes>
      <DiscreteEvent index="0">
        <Attributes>
          <userData type="uint">0</userData>
          <startTime type="double">0.00333333</startTime>
        </Attributes>
      </DiscreteEvent>
    </DiscreteEventTrack>
    <DurationEventTrack name="TimeAct" guid="7b7a4574-bd17-4c34-8a86-cc26e48b3391" channelID="2">
      <Attributes>
        <userData type="uint">1000</userData>
      </Attributes>
      <DurationEvent index="0">
        <Attributes>
          <userData type="uint">75017110</userData>
          <startTime type="double">0</startTime>
          <duration type="double">1</duration>
        </Attributes>
      </DurationEvent>
    </DurationEventTrack>
    <DurationEventTrack name="TalkDuration" guid="5afb7875-8b43-496a-9660-50195f900db0" channelID="4">
      <Attributes>
        <userData type="uint">100</userData>
      </Attributes>
      <DurationEvent index="0">
        <Attributes>
          <userData type="uint">118</userData>
          <startTime type="double">0</startTime>
          <duration type="double">1</duration>
        </Attributes>
      </DurationEvent>
    </DurationEventTrack>
  </Take>
</TakeList>